Metadata-Version: 2.4
Name: mcp-server-bigdata
Version: 0.1.0
Summary: Bigdata.com MCP Server
Author-email: Bigdata Team <support@bigdata.com>
Requires-Python: >=3.11
Requires-Dist: mcp[cli]>=1.6.0
